{
    "title": "CLDF dataset derived from Z'graggen's \"Madang Comparative Wordlists\" from 1980",
    "access_right": "open",
    "keywords": [
        "cldf:Wordlist",
        "linguistics"
    ],
    "creators": [
        {
            "name": "Tiago Tresoldi"
        },
        {
            "name": "Mattis List"
        },
        {
            "name": "Simon J. Greenhill"
        }
    ],
    "contributors": [],
    "communities": [
        {
            "identifier": "lexibank"
        }
    ],
    "upload_type": "dataset",
    "description": "<p>Cite the source of the dataset as:</p>\n\n<blockquote>\n<p>Z&#x27;graggen, J A. (1980) A comparative word list of the Northern Adelbert Range Languages, Madang Province, Papua New Guinea. Canberra: Pacific Linguistics.</p>\n</blockquote>",
    "license": {
        "id": "CC-BY-NC-4.0"
    }
}